README.rst
setup.py
feedr/__init__.py
feedr/cli.py
feedr/dictconfig.py
feedr/feedr.py
feedr/format_mappings.py
feedr/formatters.py
feedr/logger.py
feedr/six.py
feedr/transports.py
feedr.egg-info/PKG-INFO
feedr.egg-info/SOURCES.txt
feedr.egg-info/dependency_links.txt
feedr.egg-info/entry_points.txt
feedr.egg-info/requires.txt
feedr.egg-info/top_level.txt