Metadata-Version: 1.1
Name: feedr
Version: 0.4.3
Summary: Data feedr using different transports
Home-page: https://github.com/nir0s/feedr
Author: nir0s
Author-email: nir36g@gmail.com
License: LICENSE
Download-URL: https://github.com/nir0s/feedr/tarball/0.1
Platform: All
Classifier: Programming Language :: Python
Classifier: Development Status :: 3 - Alpha
Classifier: Natural Language :: English
Classifier: Environment :: Console
Classifier: Intended Audience :: Developers
Classifier: Intended Audience :: Information Technology
Classifier: Intended Audience :: System Administrators
Classifier: License :: OSI Approved :: Apache Software License
Classifier: Operating System :: POSIX :: Linux
Classifier: Operating System :: Microsoft
Classifier: Topic :: Software Development :: Libraries :: Python Modules
Classifier: Topic :: Software Development :: Testing
Classifier: Topic :: System :: Logging
